pytest_rocketchat/__init__.py
pytest_rocketchat/plugin.py
pytest_rocketchat/rocketchat.py
pytest_rocketchat-1.1.1.dist-info/entry_points.txt
pytest_rocketchat-1.1.1.dist-info/LICENSE
pytest_rocketchat-1.1.1.dist-info/WHEEL
pytest_rocketchat-1.1.1.dist-info/METADATA
pytest_rocketchat-1.1.1.dist-info/RECORD
